<?xml version="1.0" encoding="UTF-8" ?>
<dataSample><configurations><config><name><![CDATA[LEO_MENUSIDEBAR_PARAMS]]></name><value><![CDATA[[null,null,null,null,null,null,null,null,null,null]]]></value></config><config><name><![CDATA[LEO_MENUSIDEBAR_TYPE]]></name><value><![CDATA[left]]></value></config><config><name><![CDATA[LEO_MENUSIDEBAR_VERSION]]></name><value><![CDATA[3.0]]></value></config></configurations><fields objectName="Sbmegamenu" objectFile="Sbmegamenu.php" searchField="id_shop"><field><id>58</id><image><![CDATA[Untitled-3_03.png]]></image><id_parent>1</id_parent><is_group>0</is_group><width><![CDATA[]]></width><submenu_width><![CDATA[]]></submenu_width><submenu_colum_width><![CDATA[]]></submenu_colum_width><item><![CDATA[]]></item><colums><![CDATA[1]]></colums><type><![CDATA[url]]></type><is_content>0</is_content><show_title>1</show_title><is_cattree>1</is_cattree><level_depth>1</level_depth><active>1</active><position>0</position><show_sub>0</show_sub><url><en><![CDATA[#]]></en><fr><![CDATA[#]]></fr><ar><![CDATA[#]]></ar></url><target><![CDATA[_self]]></target><privacy>0</privacy><position_type><![CDATA[]]></position_type><menu_class><![CDATA[]]></menu_class><icon_class><![CDATA[]]></icon_class><content><![CDATA[]]></content><submenu_content><![CDATA[]]></submenu_content><level>0</level><left>0</left><right>0</right><date_add><![CDATA[2015-08-06 07:47:22]]></date_add><date_upd><![CDATA[2015-08-06 07:47:22]]></date_upd><title><en><![CDATA[Big Buddha]]></en><fr><![CDATA[Big Buddha]]></fr><ar><![CDATA[Big Buddha]]></ar></title><text><en><![CDATA[Mauris nibh enim]]></en><fr><![CDATA[Mauris nibh enim]]></fr><ar><![CDATA[Mauris nibh enim]]></ar></text><description><en><![CDATA[]]></en><fr><![CDATA[]]></fr><ar><![CDATA[]]></ar></description><content_text><en><![CDATA[]]></en><fr><![CDATA[]]></fr><ar><![CDATA[]]></ar></content_text><submenu_catids><![CDATA[]]></submenu_catids><params><![CDATA[null]]></params></field><field><id>59</id><image><![CDATA[Untitled-3_06.png]]></image><id_parent>1</id_parent><is_group>0</is_group><width><![CDATA[]]></width><submenu_width><![CDATA[]]></submenu_width><submenu_colum_width><![CDATA[]]></submenu_colum_width><item><![CDATA[1]]></item><colums><![CDATA[1]]></colums><type><![CDATA[cms]]></type><is_content>0</is_content><show_title>1</show_title><is_cattree>1</is_cattree><level_depth>1</level_depth><active>1</active><position>1</position><show_sub>0</show_sub><url><en><![CDATA[#]]></en><fr><![CDATA[#]]></fr><ar><![CDATA[#]]></ar></url><target><![CDATA[_self]]></target><privacy>0</privacy><position_type><![CDATA[]]></position_type><menu_class><![CDATA[]]></menu_class><icon_class><![CDATA[]]></icon_class><content><![CDATA[]]></content><submenu_content><![CDATA[]]></submenu_content><level>0</level><left>0</left><right>0</right><date_add><![CDATA[2015-08-06 07:47:23]]></date_add><date_upd><![CDATA[2015-08-06 07:47:23]]></date_upd><title><en><![CDATA[Betsey Johnson]]></en><fr><![CDATA[Betsey Johnson]]></fr><ar><![CDATA[Betsey Johnson]]></ar></title><text><en><![CDATA[Curabitur sed turpis ]]></en><fr><![CDATA[Curabitur sed turpis ]]></fr><ar><![CDATA[Curabitur sed turpis ]]></ar></text><description><en><![CDATA[]]></en><fr><![CDATA[]]></fr><ar><![CDATA[]]></ar></description><content_text><en><![CDATA[]]></en><fr><![CDATA[]]></fr><ar><![CDATA[]]></ar></content_text><submenu_catids><![CDATA[]]></submenu_catids><params><![CDATA[{"submenu":1,"cols":1,"group":0,"id":59,"rows":[{"cols":[{"colwidth":12,"type":"menu"}]}]}]]></params></field><field><id>60</id><image><![CDATA[Untitled-3_08.png]]></image><id_parent>1</id_parent><is_group>0</is_group><width><![CDATA[]]></width><submenu_width><![CDATA[]]></submenu_width><submenu_colum_width><![CDATA[]]></submenu_colum_width><item><![CDATA[1]]></item><colums><![CDATA[1]]></colums><type><![CDATA[manufacture]]></type><is_content>0</is_content><show_title>1</show_title><is_cattree>1</is_cattree><level_depth>1</level_depth><active>1</active><position>2</position><show_sub>0</show_sub><url><en><![CDATA[#]]></en><fr><![CDATA[#]]></fr><ar><![CDATA[#]]></ar></url><target><![CDATA[_self]]></target><privacy>0</privacy><position_type><![CDATA[]]></position_type><menu_class><![CDATA[]]></menu_class><icon_class><![CDATA[]]></icon_class><content><![CDATA[]]></content><submenu_content><![CDATA[]]></submenu_content><level>0</level><left>0</left><right>0</right><date_add><![CDATA[2015-08-06 07:47:23]]></date_add><date_upd><![CDATA[2015-08-06 07:47:23]]></date_upd><title><en><![CDATA[Quam ultricies]]></en><fr><![CDATA[Quam ultricies]]></fr><ar><![CDATA[Quam ultricies]]></ar></title><text><en><![CDATA[Nulla suscipit arcu]]></en><fr><![CDATA[Nulla suscipit arcu]]></fr><ar><![CDATA[Nulla suscipit arcu]]></ar></text><description><en><![CDATA[]]></en><fr><![CDATA[]]></fr><ar><![CDATA[]]></ar></description><content_text><en><![CDATA[]]></en><fr><![CDATA[]]></fr><ar><![CDATA[]]></ar></content_text><submenu_catids><![CDATA[]]></submenu_catids><params><![CDATA[null]]></params></field><field><id>61</id><image><![CDATA[Untitled-3_10.png]]></image><id_parent>1</id_parent><is_group>0</is_group><width><![CDATA[]]></width><submenu_width><![CDATA[]]></submenu_width><submenu_colum_width><![CDATA[]]></submenu_colum_width><item><![CDATA[]]></item><colums><![CDATA[1]]></colums><type><![CDATA[url]]></type><is_content>0</is_content><show_title>1</show_title><is_cattree>1</is_cattree><level_depth>1</level_depth><active>1</active><position>3</position><show_sub>0</show_sub><url><en><![CDATA[contact]]></en><fr><![CDATA[contact]]></fr><ar><![CDATA[contact]]></ar></url><target><![CDATA[_self]]></target><privacy>0</privacy><position_type><![CDATA[]]></position_type><menu_class><![CDATA[]]></menu_class><icon_class><![CDATA[]]></icon_class><content><![CDATA[]]></content><submenu_content><![CDATA[]]></submenu_content><level>0</level><left>0</left><right>0</right><date_add><![CDATA[2015-08-06 07:47:24]]></date_add><date_upd><![CDATA[2015-08-06 07:47:24]]></date_upd><title><en><![CDATA[Dolce & Gabbana]]></en><fr><![CDATA[Dolce & Gabbana]]></fr><ar><![CDATA[Dolce & Gabbana]]></ar></title><text><en><![CDATA[Nam adipiscing erat]]></en><fr><![CDATA[Nam adipiscing erat]]></fr><ar><![CDATA[Nam adipiscing erat]]></ar></text><description><en><![CDATA[]]></en><fr><![CDATA[]]></fr><ar><![CDATA[]]></ar></description><content_text><en><![CDATA[]]></en><fr><![CDATA[]]></fr><ar><![CDATA[]]></ar></content_text><submenu_catids><![CDATA[]]></submenu_catids><params><![CDATA[null]]></params></field><field><id>62</id><image><![CDATA[Untitled-3_12.png]]></image><id_parent>1</id_parent><is_group>0</is_group><width><![CDATA[]]></width><submenu_width><![CDATA[]]></submenu_width><submenu_colum_width><![CDATA[]]></submenu_colum_width><item><![CDATA[]]></item><colums><![CDATA[1]]></colums><type><![CDATA[url]]></type><is_content>0</is_content><show_title>1</show_title><is_cattree>1</is_cattree><level_depth>1</level_depth><active>1</active><position>4</position><show_sub>0</show_sub><url><en><![CDATA[sitemap]]></en><fr><![CDATA[sitemap]]></fr><ar><![CDATA[sitemap]]></ar></url><target><![CDATA[_self]]></target><privacy>0</privacy><position_type><![CDATA[]]></position_type><menu_class><![CDATA[]]></menu_class><icon_class><![CDATA[]]></icon_class><content><![CDATA[]]></content><submenu_content><![CDATA[]]></submenu_content><level>0</level><left>0</left><right>0</right><date_add><![CDATA[2015-08-06 07:47:25]]></date_add><date_upd><![CDATA[2015-08-06 07:47:25]]></date_upd><title><en><![CDATA[Elizabeth Arden]]></en><fr><![CDATA[Elizabeth Arden]]></fr><ar><![CDATA[Elizabeth Arden]]></ar></title><text><en><![CDATA[Sed a gravida libero ]]></en><fr><![CDATA[Sed a gravida libero ]]></fr><ar><![CDATA[Sed a gravida libero ]]></ar></text><description><en><![CDATA[]]></en><fr><![CDATA[]]></fr><ar><![CDATA[]]></ar></description><content_text><en><![CDATA[]]></en><fr><![CDATA[]]></fr><ar><![CDATA[]]></ar></content_text><submenu_catids><![CDATA[]]></submenu_catids><params><![CDATA[null]]></params></field><field><id>63</id><image><![CDATA[Untitled-3_14.png]]></image><id_parent>1</id_parent><is_group>0</is_group><width><![CDATA[]]></width><submenu_width><![CDATA[]]></submenu_width><submenu_colum_width><![CDATA[]]></submenu_colum_width><item><![CDATA[]]></item><colums><![CDATA[1]]></colums><type><![CDATA[url]]></type><is_content>0</is_content><show_title>1</show_title><is_cattree>1</is_cattree><level_depth>1</level_depth><active>0</active><position>5</position><show_sub>0</show_sub><url><en><![CDATA[#]]></en><fr><![CDATA[#]]></fr><ar><![CDATA[#]]></ar></url><target><![CDATA[_self]]></target><privacy>0</privacy><position_type><![CDATA[]]></position_type><menu_class><![CDATA[]]></menu_class><icon_class><![CDATA[]]></icon_class><content><![CDATA[]]></content><submenu_content><![CDATA[]]></submenu_content><level>0</level><left>0</left><right>0</right><date_add><![CDATA[2015-08-06 07:47:26]]></date_add><date_upd><![CDATA[2015-08-06 07:47:26]]></date_upd><title><en><![CDATA[Morbi euismod ]]></en><fr><![CDATA[Morbi euismod ]]></fr><ar><![CDATA[Morbi euismod ]]></ar></title><text><en><![CDATA[Nulla suscipit arcu]]></en><fr><![CDATA[Nulla suscipit arcu]]></fr><ar><![CDATA[Nulla suscipit arcu]]></ar></text><description><en><![CDATA[]]></en><fr><![CDATA[]]></fr><ar><![CDATA[]]></ar></description><content_text><en><![CDATA[]]></en><fr><![CDATA[]]></fr><ar><![CDATA[]]></ar></content_text><submenu_catids><![CDATA[]]></submenu_catids><params><![CDATA[null]]></params></field><field><id>64</id><image><![CDATA[Untitled-3_16.png]]></image><id_parent>1</id_parent><is_group>0</is_group><width><![CDATA[]]></width><submenu_width><![CDATA[]]></submenu_width><submenu_colum_width><![CDATA[]]></submenu_colum_width><item><![CDATA[]]></item><colums><![CDATA[1]]></colums><type><![CDATA[url]]></type><is_content>0</is_content><show_title>1</show_title><is_cattree>1</is_cattree><level_depth>1</level_depth><active>0</active><position>6</position><show_sub>0</show_sub><url><en><![CDATA[#]]></en><fr><![CDATA[#]]></fr><ar><![CDATA[#]]></ar></url><target><![CDATA[_self]]></target><privacy>0</privacy><position_type><![CDATA[]]></position_type><menu_class><![CDATA[]]></menu_class><icon_class><![CDATA[]]></icon_class><content><![CDATA[]]></content><submenu_content><![CDATA[]]></submenu_content><level>0</level><left>0</left><right>0</right><date_add><![CDATA[2015-08-06 07:47:27]]></date_add><date_upd><![CDATA[2015-08-06 07:47:27]]></date_upd><title><en><![CDATA[Estee Lauder ]]></en><fr><![CDATA[Estee Lauder ]]></fr><ar><![CDATA[Estee Lauder ]]></ar></title><text><en><![CDATA[Mauris nibh enim]]></en><fr><![CDATA[Mauris nibh enim]]></fr><ar><![CDATA[Mauris nibh enim]]></ar></text><description><en><![CDATA[]]></en><fr><![CDATA[]]></fr><ar><![CDATA[]]></ar></description><content_text><en><![CDATA[]]></en><fr><![CDATA[]]></fr><ar><![CDATA[]]></ar></content_text><submenu_catids><![CDATA[]]></submenu_catids><params><![CDATA[null]]></params></field><field><id>65</id><image><![CDATA[Untitled-3_18.png]]></image><id_parent>1</id_parent><is_group>0</is_group><width><![CDATA[]]></width><submenu_width><![CDATA[]]></submenu_width><submenu_colum_width><![CDATA[]]></submenu_colum_width><item><![CDATA[]]></item><colums><![CDATA[1]]></colums><type><![CDATA[url]]></type><is_content>0</is_content><show_title>1</show_title><is_cattree>1</is_cattree><level_depth>1</level_depth><active>0</active><position>7</position><show_sub>0</show_sub><url><en><![CDATA[#]]></en><fr><![CDATA[#]]></fr><ar><![CDATA[#]]></ar></url><target><![CDATA[_self]]></target><privacy>0</privacy><position_type><![CDATA[]]></position_type><menu_class><![CDATA[]]></menu_class><icon_class><![CDATA[]]></icon_class><content><![CDATA[]]></content><submenu_content><![CDATA[]]></submenu_content><level>0</level><left>0</left><right>0</right><date_add><![CDATA[2015-08-06 07:47:27]]></date_add><date_upd><![CDATA[2015-08-06 07:47:27]]></date_upd><title><en><![CDATA[Giorgio Armani]]></en><fr><![CDATA[Giorgio Armani]]></fr><ar><![CDATA[Giorgio Armani]]></ar></title><text><en><![CDATA[Lorem ipsum dolor sit ]]></en><fr><![CDATA[Lorem ipsum dolor sit ]]></fr><ar><![CDATA[Lorem ipsum dolor sit ]]></ar></text><description><en><![CDATA[]]></en><fr><![CDATA[]]></fr><ar><![CDATA[]]></ar></description><content_text><en><![CDATA[]]></en><fr><![CDATA[]]></fr><ar><![CDATA[]]></ar></content_text><submenu_catids><![CDATA[]]></submenu_catids><params><![CDATA[null]]></params></field><field><id>66</id><image><![CDATA[Untitled-3_20.png]]></image><id_parent>1</id_parent><is_group>0</is_group><width><![CDATA[]]></width><submenu_width><![CDATA[]]></submenu_width><submenu_colum_width><![CDATA[]]></submenu_colum_width><item><![CDATA[]]></item><colums><![CDATA[1]]></colums><type><![CDATA[url]]></type><is_content>0</is_content><show_title>1</show_title><is_cattree>1</is_cattree><level_depth>1</level_depth><active>1</active><position>8</position><show_sub>0</show_sub><url><en><![CDATA[#]]></en><fr><![CDATA[#]]></fr><ar><![CDATA[#]]></ar></url><target><![CDATA[_self]]></target><privacy>0</privacy><position_type><![CDATA[]]></position_type><menu_class><![CDATA[]]></menu_class><icon_class><![CDATA[]]></icon_class><content><![CDATA[]]></content><submenu_content><![CDATA[]]></submenu_content><level>0</level><left>0</left><right>0</right><date_add><![CDATA[2015-08-06 07:47:28]]></date_add><date_upd><![CDATA[2015-08-06 07:47:28]]></date_upd><title><en><![CDATA[Givenchy Cologne ]]></en><fr><![CDATA[Givenchy Cologne ]]></fr><ar><![CDATA[Givenchy Cologne ]]></ar></title><text><en><![CDATA[Maecenas libero mauris]]></en><fr><![CDATA[Maecenas libero mauris]]></fr><ar><![CDATA[Maecenas libero mauris]]></ar></text><description><en><![CDATA[]]></en><fr><![CDATA[]]></fr><ar><![CDATA[]]></ar></description><content_text><en><![CDATA[]]></en><fr><![CDATA[]]></fr><ar><![CDATA[]]></ar></content_text><submenu_catids><![CDATA[]]></submenu_catids><params><![CDATA[null]]></params></field><field><id>67</id><image><![CDATA[Untitled-3_22.png]]></image><id_parent>1</id_parent><is_group>0</is_group><width><![CDATA[]]></width><submenu_width><![CDATA[]]></submenu_width><submenu_colum_width><![CDATA[]]></submenu_colum_width><item><![CDATA[1]]></item><colums><![CDATA[1]]></colums><type><![CDATA[cms]]></type><is_content>0</is_content><show_title>1</show_title><is_cattree>1</is_cattree><level_depth>1</level_depth><active>1</active><position>9</position><show_sub>0</show_sub><url><en><![CDATA[]]></en><fr><![CDATA[]]></fr><ar><![CDATA[]]></ar></url><target><![CDATA[_self]]></target><privacy>0</privacy><position_type><![CDATA[]]></position_type><menu_class><![CDATA[]]></menu_class><icon_class><![CDATA[]]></icon_class><content><![CDATA[]]></content><submenu_content><![CDATA[]]></submenu_content><level>0</level><left>0</left><right>0</right><date_add><![CDATA[2015-08-06 07:47:29]]></date_add><date_upd><![CDATA[2015-08-06 07:47:29]]></date_upd><title><en><![CDATA[Typography]]></en><fr><![CDATA[Typography]]></fr><ar><![CDATA[Typography]]></ar></title><text><en><![CDATA[Quisque ac neque et augue]]></en><fr><![CDATA[Quisque ac neque et augue]]></fr><ar><![CDATA[Quisque ac neque et augue]]></ar></text><description><en><![CDATA[]]></en><fr><![CDATA[]]></fr><ar><![CDATA[]]></ar></description><content_text><en><![CDATA[]]></en><fr><![CDATA[]]></fr><ar><![CDATA[]]></ar></content_text><submenu_catids><![CDATA[]]></submenu_catids><params><![CDATA[null]]></params></field></fields><sql><![CDATA[CREATE TABLE IF NOT EXISTS `PREFIX_sbmegamenu` (
  `id_sbmegamenu` int(11) NOT NULL AUTO_INCREMENT,
  `image` varchar(255) NOT NULL,
  `id_parent` int(11) NOT NULL,
  `is_group` tinyint(1) NOT NULL,
  `width` varchar(255) DEFAULT NULL,
  `submenu_width` varchar(255) DEFAULT NULL,
  `submenu_colum_width` varchar(255) DEFAULT NULL,
  `item` varchar(255) DEFAULT NULL,
  `colums` varchar(255) DEFAULT NULL,
  `type` varchar(255) NOT NULL,
  `is_content` tinyint(1) NOT NULL,
  `show_title` tinyint(1) NOT NULL,
  `type_submenu` varchar(10) NOT NULL,
  `level_depth` smallint(6) NOT NULL,
  `active` tinyint(1) NOT NULL,
  `position` int(11) NOT NULL,
  `submenu_content` text NOT NULL,
  `show_sub` tinyint(1) NOT NULL,
  `target` varchar(25) DEFAULT NULL,
  `privacy` smallint(6) DEFAULT NULL,
  `position_type` varchar(25) DEFAULT NULL,
  `menu_class` varchar(25) DEFAULT NULL,
  `content` text,
  `icon_class` varchar(255) DEFAULT NULL,
  `level` int(11) NOT NULL,
  `left` int(11) NOT NULL,
  `right` int(11) NOT NULL,
  `submenu_catids` text,
  `is_cattree` tinyint(1) DEFAULT '1',
  `date_add` datetime DEFAULT NULL,
  `date_upd` datetime DEFAULT NULL,
  PRIMARY KEY (`id_sbmegamenu`)
) ENGINE=ENGINE_TYPE AUTO_INCREMENT=68 DEFAULT CHARSET=utf8;

CREATE TABLE IF NOT EXISTS `PREFIX_sbmegamenu_lang` (
  `id_sbmegamenu` int(11) NOT NULL,
  `id_lang` int(11) NOT NULL,
  `title` varchar(255) DEFAULT NULL,
  `text` varchar(255) DEFAULT NULL,
  `description` text,
  `content_text` text,
  `submenu_content_text` text,
  `url` varchar(255) DEFAULT NULL,
  PRIMARY KEY (`id_sbmegamenu`,`id_lang`)
) ENGINE=ENGINE_TYPE DEFAULT CHARSET=utf8;

CREATE TABLE IF NOT EXISTS `PREFIX_sbmegamenu_shop` (
  `id_sbmegamenu` int(11) NOT NULL DEFAULT '0',
  `id_shop` int(11) NOT NULL DEFAULT '0',
  PRIMARY KEY (`id_sbmegamenu`,`id_shop`)
) ENGINE=ENGINE_TYPE DEFAULT CHARSET=utf8;

]]></sql><hooks></hooks></dataSample>